neatutils/__init__.py
neatutils/neatutils.py
neatutils-0.0.1.dist-info/LICENSE
neatutils-0.0.1.dist-info/WHEEL
neatutils-0.0.1.dist-info/METADATA
neatutils-0.0.1.dist-info/RECORD
