Metadata-Version: 2.1
Name: neatutils
Version: 0.0.1
Summary: NeatUtils - a simple reference utility for awesome lists and machine learning estimators and algorithms
Home-page: https://github.com/Jcharis/neatutils
License: MIT
Keywords: neatutils,awesome list,machine learning estimators,ml algorithms list,sklearn estimators,neat,jcharis,list pycaret estimators,distutils
Author: Jesse E.Agbe(JCharis)
Author-email: jcharistech@gmail.com
Requires-Python: >=3.3,<4.0
Classifier: License :: OSI Approved :: MIT License
Classifier: Operating System :: OS Independent
Classifier: Programming Language :: Python :: 3
Classifier: Programming Language :: Python :: 3.4
Classifier: Programming Language :: Python :: 3.5
Classifier: Programming Language :: Python :: 3.6
Classifier: Programming Language :: Python :: 3.7
Classifier: Programming Language :: Python :: 3.8
Requires-Dist: click (>=7.1.2,<8.0.0)
Requires-Dist: click-help-colors (>=0.8,<0.9)
Project-URL: Repository, https://github.com/Jcharis/neatutils
